charinfo/__init__.py
charinfo/__main__.py
charinfo/core.py
charinfo-0.2.0.dist-info/LICENSE
charinfo-0.2.0.dist-info/METADATA
charinfo-0.2.0.dist-info/WHEEL
charinfo-0.2.0.dist-info/entry_points.txt
charinfo-0.2.0.dist-info/top_level.txt
charinfo-0.2.0.dist-info/RECORD
