Metadata-Version: 2.1
Name: charinfo
Version: 0.2.0
Summary: A command line tool to view detailed information about a character
Home-page: UNKNOWN
Author: Wasi Master
Author-email: arianmollik323@gmail.com
License: MIT
Project-URL: Bug Tracker, https://github.com/wasi-master/charinfo/issues
Project-URL: Source, https://github.com/wasi-master/charinfo
Project-URL: Say Thanks, https://saythanks.io/to/wasi-master
Keywords: charinfo,cli,char,character,characters,character information,character-information,charinfo-cli,charinfo cli,character-info,character info,character-info-cli,character info cli
Platform: UNKNOWN
Classifier: Programming Language :: Python :: 3
Classifier: Programming Language :: Python :: 3.6
Classifier: Programming Language :: Python :: 3.7
Classifier: Programming Language :: Python :: 3.8
Classifier: Programming Language :: Python :: 3.9
Classifier: Programming Language :: Python :: 3.10
Classifier: License :: OSI Approved :: MIT License
Classifier: Operating System :: OS Independent
Classifier: Development Status :: 4 - Beta
Classifier: Environment :: Console
Classifier: Intended Audience :: Developers
Classifier: Intended Audience :: End Users/Desktop
Classifier: Natural Language :: English
Classifier: Topic :: Terminals
License-File: LICENSE
Requires-Dist: rich
